MANIFEST.in
README.txt
manage.py
setup.py
arches_hip/__init__.py
arches_hip/__main__.py
arches_hip/settings.py
arches_hip/setup.py
arches_hip/urls.py
arches_hip.egg-info/PKG-INFO
arches_hip.egg-info/SOURCES.txt
arches_hip.egg-info/dependency_links.txt
arches_hip.egg-info/not-zip-safe
arches_hip.egg-info/requires.txt
arches_hip.egg-info/top_level.txt
arches_hip/logs/__init__.py
arches_hip/media/css/reports.css
arches_hip/media/js/resource-report.js
arches_hip/media/js/views/forms/activity-actions.js
arches_hip/media/js/views/forms/activity-summary.js
arches_hip/media/js/views/forms/actor-summary.js
arches_hip/media/js/views/forms/classification.js
arches_hip/media/js/views/forms/component.js
arches_hip/media/js/views/forms/condition.js
arches_hip/media/js/views/forms/coverage.js
arches_hip/media/js/views/forms/description.js
arches_hip/media/js/views/forms/designation.js
arches_hip/media/js/views/forms/district_classification.js
arches_hip/media/js/views/forms/evaluation.js
arches_hip/media/js/views/forms/external-reference.js
arches_hip/media/js/views/forms/file-upload.js
arches_hip/media/js/views/forms/historical-event-summary.js
arches_hip/media/js/views/forms/information-resource-summary.js
arches_hip/media/js/views/forms/location.js
arches_hip/media/js/views/forms/measurement.js
arches_hip/media/js/views/forms/phase.js
arches_hip/media/js/views/forms/publication.js
arches_hip/media/js/views/forms/related-files.js
arches_hip/media/js/views/forms/related-resources.js
arches_hip/media/js/views/forms/roles.js
arches_hip/media/js/views/forms/summary.js
arches_hip/models/__init__.py
arches_hip/models/forms.py
arches_hip/models/resource.py
arches_hip/source_data/__init__.py
arches_hip/source_data/resource_graphs/ACTIVITY.E7.gephi
arches_hip/source_data/resource_graphs/ACTIVITY.E7_edges.csv
arches_hip/source_data/resource_graphs/ACTIVITY.E7_nodes.csv
arches_hip/source_data/resource_graphs/ACTOR.E39.gephi
arches_hip/source_data/resource_graphs/ACTOR.E39_edges.csv
arches_hip/source_data/resource_graphs/ACTOR.E39_nodes.csv
arches_hip/source_data/resource_graphs/HERITAGE_RESOURCE.E18.gephi
arches_hip/source_data/resource_graphs/HERITAGE_RESOURCE.E18_edges.csv
