Metadata-Version: 1.1
Name: arches-hip
Version: 1.0.4
Summary: The Heritage Information Package (HIP)
Home-page: http://archesproject.org/
Author: Farallon Geographics, Inc
Author-email: dev@fargeo.com
License: GNU AGPL
Keywords: django arches hip cultural heritage
Platform: UNKNOWN
Classifier: Development Status :: 5 - Production/Stable
Classifier: Intended Audience :: Developers
Classifier: Topic :: Software Development :: Build Tools
Classifier: Programming Language :: Python :: 2
Classifier: Programming Language :: Python :: 2.7
